mcp_goodnews/__init__.py
mcp_goodnews/goodnews_ranker.py
mcp_goodnews/newsapi.py
mcp_goodnews/server.py
mseep_mcp_goodnews-0.1.1.dist-info/licenses/LICENSE
mseep_mcp_goodnews-0.1.1.dist-info/METADATA
mseep_mcp_goodnews-0.1.1.dist-info/WHEEL
mseep_mcp_goodnews-0.1.1.dist-info/top_level.txt
mseep_mcp_goodnews-0.1.1.dist-info/RECORD
