Metadata-Version: 2.4
Name: mseep-mcp-goodnews
Version: 0.1.1
Summary: An MCP application that delivers curated positive and uplifting news stories.
Author-email: mseep <support@skydeck.ai>
Requires-Python: >=3.11
License-File: LICENSE
Requires-Dist: asyncio>=3.4.3
Requires-Dist: cohere>=5.14.0
Requires-Dist: mcp[cli]>=1.4.1
Requires-Dist: pydantic>=2.10.6
Dynamic: license-file
